passport_mrz_extractor/__init__.py
passport_mrz_extractor/mrz_reader.py
passport_mrz_extractor-1.0.2.dist-info/METADATA
passport_mrz_extractor-1.0.2.dist-info/WHEEL
passport_mrz_extractor-1.0.2.dist-info/top_level.txt
passport_mrz_extractor-1.0.2.dist-info/RECORD
