Metadata-Version: 2.1
Name: passport_mrz_extractor
Version: 1.0.2
Summary: A Python library for reading MRZ data from passport images using Tesseract OCR
Home-page: https://github.com/Azim-Kenzh/passport_mrz_extractor
Author: Azimkozho Kenzhebek uulu
Author-email: azimkozho.inventor@gmail.com
License: MIT
Keywords: MRZ passport OCR Tesseract image-processing
Classifier: Development Status :: 4 - Beta
Classifier: Intended Audience :: Developers
Classifier: License :: OSI Approved :: MIT License
Classifier: Programming Language :: Python :: 3
Classifier: Programming Language :: Python :: 3.7
Classifier: Programming Language :: Python :: 3.8
Classifier: Programming Language :: Python :: 3.9
Classifier: Programming Language :: Python :: 3.10
Classifier: Topic :: Software Development :: Libraries :: Python Modules
Classifier: Topic :: Multimedia :: Graphics :: Capture :: Scanners
Requires-Python: >=3.10
Requires-Dist: Pillow
Requires-Dist: pytesseract
Requires-Dist: opencv-python
Requires-Dist: mrz
